mwdocker/__init__.py
mwdocker/config.py
mwdocker/docker.py
mwdocker/docker_map.py
mwdocker/html_table.py
mwdocker/logger.py
mwdocker/mariadb.py
mwdocker/mw.py
mwdocker/mwcluster.py
mwdocker/mwdocker_cmd.py
mwdocker/version.py
mwdocker/webscrape.py
mwdocker/resources/extensions.yaml
mwdocker/resources/templates/addSysopUser.sh
mwdocker/resources/templates/disable_sudo.sh
mwdocker/resources/templates/installExtensions.sh
mwdocker/resources/templates/install_djvu.sh
mwdocker/resources/templates/mwCompose.yml
mwdocker/resources/templates/mwComposeExternalDB.yml
mwdocker/resources/templates/mwDockerfile
mwdocker/resources/templates/mwLocalSettings.php
mwdocker/resources/templates/mwLocalSettings127.php
mwdocker/resources/templates/mwLocalSettings135.php
mwdocker/resources/templates/mwLocalSettings139.php
mwdocker/resources/templates/mwLocalSettings143.php
mwdocker/resources/templates/mwLocalSettings144.php
mwdocker/resources/templates/mwLocalSettings145.php
mwdocker/resources/templates/mwLocalSettings_path.php
mwdocker/resources/templates/mwWiki127.sql
mwdocker/resources/templates/mwWiki131.sql
mwdocker/resources/templates/mwWiki135.sql
mwdocker/resources/templates/mwWiki136.sql
mwdocker/resources/templates/mwWiki137.sql
mwdocker/resources/templates/mwWiki138.sql
mwdocker/resources/templates/mwWiki139.sql
mwdocker/resources/templates/mwWiki140.sql
mwdocker/resources/templates/mwWiki141.sql
mwdocker/resources/templates/mwWiki142.sql
mwdocker/resources/templates/mwWiki143.sql
mwdocker/resources/templates/mwWiki144.sql
mwdocker/resources/templates/mwWiki145.sql
mwdocker/resources/templates/my.cnf
mwdocker/resources/templates/phpinfo.php
mwdocker/resources/templates/plantuml.sh
mwdocker/resources/templates/setup-mediawiki-legacy.sh
mwdocker/resources/templates/setup-mediawiki.sh
mwdocker/resources/templates/upload.ini
pymediawikidocker-0.23.5.dist-info/METADATA
pymediawikidocker-0.23.5.dist-info/WHEEL
pymediawikidocker-0.23.5.dist-info/entry_points.txt
pymediawikidocker-0.23.5.dist-info/licenses/LICENSE
pymediawikidocker-0.23.5.dist-info/RECORD
