Metadata-Version: 2.4
Name: pymediawikidocker
Version: 0.23.5
Summary: Python controlled (semantic) mediawiki docker application cluster installation
Project-URL: Home, https://github.com/WolfgangFahl/pymediawikidocker
Project-URL: Documentation, https://wiki.bitplan.com/index.php/pymediawikidocker
Project-URL: Source, https://github.com/WolfgangFahl/pymediawikidocker
Author-email: Wolfgang Fahl <wf@bitplan.com>
Maintainer-email: Wolfgang Fahl <wf@bitplan.com>
License: Apache-2.0
License-File: LICENSE
Classifier: Development Status :: 4 - Beta
Classifier: Environment :: Web Environment
Classifier: Intended Audience :: Developers
Classifier: Intended Audience :: Education
Classifier: Intended Audience :: Science/Research
Classifier: License :: OSI Approved :: Apache Software License
Classifier: Operating System :: OS Independent
Classifier: Programming Language :: Python :: 3 :: Only
Classifier: Programming Language :: Python :: 3.10
Classifier: Programming Language :: Python :: 3.11
Classifier: Programming Language :: Python :: 3.12
Classifier: Programming Language :: Python :: 3.13
Classifier: Topic :: Software Development :: User Interfaces
Requires-Python: >=3.10
Requires-Dist: beautifulsoup4
Requires-Dist: dacite>=1.8.1
Requires-Dist: jinja2
Requires-Dist: mysql-connector-python
Requires-Dist: py-3rdparty-mediawiki>=0.17.0
Requires-Dist: pybasemkit>=0.1.2
Requires-Dist: pylodstorage>=0.17.5
Requires-Dist: python-on-whales>=0.79.0
Requires-Dist: six
Provides-Extra: test
Requires-Dist: green; extra == 'test'
